odoo/addons/shopfloor_workstation_mobile/README.rst
odoo/addons/shopfloor_workstation_mobile/__init__.py
odoo/addons/shopfloor_workstation_mobile/__manifest__.py
odoo/addons/shopfloor_workstation_mobile/i18n/es_AR.po
odoo/addons/shopfloor_workstation_mobile/i18n/it.po
odoo/addons/shopfloor_workstation_mobile/i18n/shopfloor_workstation_mobile.pot
odoo/addons/shopfloor_workstation_mobile/static/description/icon.png
odoo/addons/shopfloor_workstation_mobile/static/description/index.html
odoo/addons/shopfloor_workstation_mobile/static/wms/.gitignore
odoo/addons/shopfloor_workstation_mobile/static/wms/src/settings/workstation.js
odoo/addons/shopfloor_workstation_mobile/templates/assets.xml
odoo13_addon_shopfloor_workstation_mobile-13.0.1.0.1.dev6.dist-info/METADATA
odoo13_addon_shopfloor_workstation_mobile-13.0.1.0.1.dev6.dist-info/WHEEL
odoo13_addon_shopfloor_workstation_mobile-13.0.1.0.1.dev6.dist-info/top_level.txt
odoo13_addon_shopfloor_workstation_mobile-13.0.1.0.1.dev6.dist-info/RECORD
